[1,0,0,[["cc.JsonAsset",["_name","json"],1]],[[0,0,1,3]],[[0,"ShopDateData",[{"index":1,"name":"et","chinese":"ET","SkinType":"none","lock_ad_num":10,"lock_fragment_num":10,"lock_fragment_company":1000},{"index":2,"name":"kitty","chinese":"猫咪","SkinType":"ad","lock_ad_num":40,"lock_fragment_num":0,"lock_fragment_company":0},{"index":3,"name":"panda","chinese":"熊猫","SkinType":"ad","lock_ad_num":40,"lock_fragment_num":0,"lock_fragment_company":0},{"index":4,"name":"cagoulards","chinese":"卡古拉","SkinType":"ad","lock_ad_num":30,"lock_fragment_num":0,"lock_fragment_company":0},{"index":5,"name":"traveler","chinese":"悟空","SkinType":"ad","lock_ad_num":30,"lock_fragment_num":0,"lock_fragment_company":0},{"index":6,"name":"champion","chinese":"球王","SkinType":"ad","lock_ad_num":30,"lock_fragment_num":0,"lock_fragment_company":0},{"index":7,"name":"shibaInu","chinese":"柴犬","SkinType":"ad","lock_ad_num":20,"lock_fragment_num":0,"lock_fragment_company":0},{"index":8,"name":"rabbit","chinese":"兔子","SkinType":"ad","lock_ad_num":20,"lock_fragment_num":0,"lock_fragment_company":0},{"index":9,"name":"dryGirl","chinese":"干物妹","SkinType":"ad","lock_ad_num":10,"lock_fragment_num":0,"lock_fragment_company":0},{"index":10,"name":"oneEye","chinese":"独眼怪","SkinType":"ad","lock_ad_num":0,"lock_fragment_num":60,"lock_fragment_company":40},{"index":11,"name":"baldHead","chinese":"光头吴克","SkinType":"fragment","lock_ad_num":0,"lock_fragment_num":60,"lock_fragment_company":40},{"index":12,"name":"bandageBear","chinese":"绷带熊","SkinType":"fragment","lock_ad_num":0,"lock_fragment_num":60,"lock_fragment_company":40},{"index":13,"name":"unicorn","chinese":"独角兽","SkinType":"fragment","lock_ad_num":0,"lock_fragment_num":60,"lock_fragment_company":40},{"index":14,"name":"pig","chinese":"猪","SkinType":"fragment","lock_ad_num":0,"lock_fragment_num":60,"lock_fragment_company":40},{"index":15,"name":"pirate","chinese":"海盗","SkinType":"fragment","lock_ad_num":0,"lock_fragment_num":60,"lock_fragment_company":40}]]],0,0,[],[],[]]